testVerilator/vsrc/CounterNextValueGenerator.v
module CounterNextValueGenerator (
	input [1:0] CurrentValue,					// 当前两位饱和计数器值 
	input				Taken,								// 1为Taken，0为NotTaken
	output[1:0] NextValue							// 下一值
);

// 使用加法器来生成两位饱和寄存器下一阶段值
assign NextValue[0] = ~CurrentValue[0] &	Taken									// 卡诺图画出来的，不要问为什么
										|  CurrentValue[1] & ~CurrentValue[0]
										|  CurrentValue[1] &  Taken						;
						 
assign NextValue[1] =  CurrentValue[0] & Taken									// 同上
										|	 CurrentValue[1] & Taken
										|  &CurrentValue											;
endmodule

work/LocalPrediction/LocalPrediction.v
module LocalPrediction (
	// 时钟信号及复位信号
	input				clk,
	input				rstn,

	// 分支预测相关信号输入输出 
	input [9:0] PredictBranchPC,			// 需要预测的PC
	output[1:0]	PredictCounter,				// 分支预测结果的饱和计数器值	

	// 饱和计数器更新相关
	input	[9:0]	CommitedBranchPC,			// 提交分支的指令PC
	input				BranchTaken,					// 当前提交分支的指令PC是否发生分支
	input	[1:0]	BranchCounter,				// 先前的分支的饱和计数器值
	input				CounterUpdate					// 是否更新当前饱和计数器
);

reg		[1:0] Counter [1024];					// 饱和计数器组

wire	[1:0] NextValue;							// 提交的分支指令的饱和计数器下一值
wire				SameAndNeedtoBeUpdate;	// 提交的分支指令需要更新且与当前预测PC相同

assign SameAndNeedtoBeUpdate = (PredictBranchPC == CommitedBranchPC) & CounterUpdate;


CounterNextValueGenerator CounterNextValueGenerator1(								// 例化计算饱和计数器下一值模块
	.CurrentValue					(	BranchCounter	),
	.Taken								( BranchTaken		),
	.NextValue						( NextValue			)
);

// 1k个两位饱和寄存器，复位状态为01（weakly not taken） 
integer i;

always @(posedge clk or negedge rstn) begin
	if (~rstn) begin
		for (i = 0; i < 1023; i=i+1) begin
			Counter[i] <= 2'b01;											// 初始化饱和计数器
		end
	end else if(CounterUpdate)begin
		Counter[CommitedBranchPC] <= NextValue;			// 更新饱和计数器
	end	
end

assign PredictCounter	= {2{~(SameAndNeedtoBeUpdate)}} & Counter[PredictBranchPC]
											| {2{ (SameAndNeedtoBeUpdate)}} & NextValue								;			// 给出预测的指令的饱和计数器结果
	

endmodule

testVerilator/wave.vcd
$version Generated by VerilatedVcd $end
$date Mon Mar  6 21:28:40 2023 $end
$timescale 1ps $end

 $scope module TOP $end
  $var wire  2 ) BranchCounter [1:0] $end
  $var wire  1 ( BranchTaken $end
  $var wire 10 ' CommitedBranchPC [9:0] $end
  $var wire  1 * CounterUpdate $end
  $var wire 10 % PredictBranchPC [9:0] $end
  $var wire  2 & PredictCounter [1:0] $end
  $var wire  1 # clk $end
  $var wire  1 $ rstn $end
  $scope module LocalPrediction $end
   $var wire  2 ) BranchCounter [1:0] $end
   $var wire  1 ( BranchTaken $end
   $var wire 10 ' CommitedBranchPC [9:0] $end
   $var wire  1 * CounterUpdate $end
   $var wire  2 + NextValue [1:0] $end
   $var wire 10 % PredictBranchPC [9:0] $end
   $var wire  2 & PredictCounter [1:0] $end
   $var wire  1 , SameAndNeedtoBeUpdate $end
   $var wire  1 # clk $end
   $var wire 32 - i [31:0] $end
   $var wire  1 $ rstn $end
   $scope module CounterNextValueGenerator1 $end
    $var wire  2 ) CurrentValue [1:0] $end
    $var wire  2 + NextValue [1:0] $end
    $var wire  1 ( Taken $end
   $upscope $end
  $upscope $end
 $upscope $end
$enddefinitions $end


#1
0#
0$
b0000000000 %
b00 &
b0000000000 '
0(
b00 )
0*
b00 +
0,
b00000000000000000000000000000000 -
#2
b01 &
b00000000000000000000001111111111 -
#3
#4
#5
#6
#7
#8
#9
#10
#11
1$
b1111111111 %
b00 &
#12
1#
b1111111111 '
1(
b01 )
b10 +
#13
0#
#14
1#
b01 &
b00 )
1*
b01 +
1,
#15
0#
#16
1#
b10 &
b01 )
b10 +
#17
0#
#18
1#
0(
b10 )
0*
b01 +
0,
#19
0#
#20
1#
b11 &
1(
1*
b11 +
1,
#21
0#
#22
1#
b10 &
0(
b11 )
b10 +
#23
0#
#24
1#
b01 &
b10 )
b01 +
#25
0#
#26
1#
1(
b01 )
0*
b10 +
0,
#27
0#
#28
1#
0(
b00 +
#29
0#
#30
1#
#31
0#
#32
1#
1(
b10 +
#33
0#
#34
1#
b10 &
1*
1,
#35
0#
#36
1#
0(
b10 )
0*
b01 +
0,
#37
0#
#38
1#
b01 &
1*
1,
#39
0#
#40
1#
b10 &
1(
b01 )
b10 +
#41
0#
#42
1#
b10 )
0*
b11 +
0,
#43
0#
#44
1#
0(
b01 +
#45
0#
#46
1#
b11 &
1(
1*
b11 +
1,
#47
0#
#48
1#
b11 )
0*
0,
#49
0#
#50
1#
#51
0#
#52
1#
1*
1,
#53
0#
#54
1#
#55
0#
#56
1#
b10 &
0(
b10 +
#57
0#
#58
1#
b10 )
0*
b01 +
0,
#59
0#
#60
1#
1(
b11 +
#61
0#
#62
1#
#63
0#
#64
1#
#65
0#
#66
1#
b01 &
0(
1*
b01 +
1,
#67
0#
#68
1#
b01 )
0*
b00 +
0,
#69
0#
#70
1#
b00 &
1*
1,
#71
0#
#72
1#
b01 &
1(
b00 )
b01 +
#73
0#
#74
1#
b00 &
0(
b01 )
b00 +
#75
0#
#76
1#
b00 )
#77
0#
#78
1#
#79
0#
#80
1#
b01 &
1(
b01 +
#81
0#
#82
1#
b00 &
0(
b01 )
b00 +
#83
0#
#84
1#
b00 )
#85
0#
#86
1#
#87
0#
#88
1#
0*
0,
#89
0#
#90
1#
1(
b01 +
